weibo_2_album/__init__.py
weibo_2_album-0.0.71.dist-info/LICENSE
weibo_2_album-0.0.71.dist-info/METADATA
weibo_2_album-0.0.71.dist-info/WHEEL
weibo_2_album-0.0.71.dist-info/top_level.txt
weibo_2_album-0.0.71.dist-info/RECORD
