Metadata-Version: 2.1
Name: weibo-2-album
Version: 0.0.71
Summary: Return photo list and caption (markdown format) from weibo.
Home-page: https://github.com/gaoyunzhi/weibo_2_album
Author: Yunzhi Gao
Author-email: gaoyunzhi@gmail.com
License: UNKNOWN
Platform: UNKNOWN
Classifier: Programming Language :: Python :: 3
Classifier: License :: OSI Approved :: MIT License
Classifier: Operating System :: OS Independent
Requires-Python: >=3.0
License-File: LICENSE
Requires-Dist: cached-url
Requires-Dist: pyyaml
Requires-Dist: bs4
Requires-Dist: lxml
Requires-Dist: telegram-util
